odoo8_addon_product_code_builder_sequence-8.0.0.0.1.99.dev11-nspkg.pth
odoo_addons/product_code_builder_sequence/README.rst
odoo_addons/product_code_builder_sequence/__init__.py
odoo_addons/product_code_builder_sequence/__openerp__.py
odoo_addons/product_code_builder_sequence/hooks.py
odoo_addons/product_code_builder_sequence/i18n/ca.po
odoo_addons/product_code_builder_sequence/i18n/de.po
odoo_addons/product_code_builder_sequence/i18n/es.po
odoo_addons/product_code_builder_sequence/i18n/fr.po
odoo_addons/product_code_builder_sequence/i18n/product_code_builder_sequence.pot
odoo_addons/product_code_builder_sequence/i18n/sl.po
odoo_addons/product_code_builder_sequence/models/__init__.py
odoo_addons/product_code_builder_sequence/models/product_product.py
odoo_addons/product_code_builder_sequence/static/description/icon.png
odoo_addons/product_code_builder_sequence/tests/__init__.py
odoo_addons/product_code_builder_sequence/tests/test_prefix.py
odoo8_addon_product_code_builder_sequence-8.0.0.0.1.99.dev11.dist-info/METADATA
odoo8_addon_product_code_builder_sequence-8.0.0.0.1.99.dev11.dist-info/WHEEL
odoo8_addon_product_code_builder_sequence-8.0.0.0.1.99.dev11.dist-info/namespace_packages.txt
odoo8_addon_product_code_builder_sequence-8.0.0.0.1.99.dev11.dist-info/top_level.txt
odoo8_addon_product_code_builder_sequence-8.0.0.0.1.99.dev11.dist-info/RECORD
