Metadata-Version: 2.1
Name: odoo8-addon-product-code-builder-sequence
Version: 8.0.0.0.1.99.dev11
Summary: Product Code Builder Sequence
Home-page: http://www.akretion.com/
Author: Akretion,Odoo Community Association (OCA)
Author-email: support@odoo-community.org
License: AGPL-3
Platform: UNKNOWN
Classifier: Programming Language :: Python
Classifier: Framework :: Odoo
Classifier: License :: OSI Approved :: GNU Affero General Public License v3
Requires-Python: ~=2.7
Requires-Dist: odoo8-addon-product-code-builder
Requires-Dist: odoo8-addon-product-sequence
Requires-Dist: odoo (<9.0a,>=8.0a)
